onlyfans_scraper/__init__.py
onlyfans_scraper/__version__.py
onlyfans_scraper/api/__init__.py
onlyfans_scraper/api/highlights.py
onlyfans_scraper/api/init.py
onlyfans_scraper/api/me.py
onlyfans_scraper/api/messages.py
onlyfans_scraper/api/paid.py
onlyfans_scraper/api/posts.py
onlyfans_scraper/api/profile.py
onlyfans_scraper/api/subscriptions.py
onlyfans_scraper/constants.py
onlyfans_scraper/db/__init__.py
onlyfans_scraper/db/operations.py
onlyfans_scraper/interaction/__init__.py
onlyfans_scraper/interaction/like.py
onlyfans_scraper/scraper.py
onlyfans_scraper/utils/__init__.py
onlyfans_scraper/utils/auth.py
onlyfans_scraper/utils/config.py
onlyfans_scraper/utils/dates.py
onlyfans_scraper/utils/decorators.py
onlyfans_scraper/utils/download.py
onlyfans_scraper/utils/encoding.py
onlyfans_scraper/utils/login.py
onlyfans_scraper/utils/nap.py
onlyfans_scraper/utils/old_nap.py
onlyfans_scraper/utils/paths.py
onlyfans_scraper/utils/profiles.py
onlyfans_scraper/utils/prompts.py
onlyfans_scraper/utils/separate.py
onlyfans_scraper2-1.2.dist-info/LICENSE
onlyfans_scraper2-1.2.dist-info/METADATA
onlyfans_scraper2-1.2.dist-info/WHEEL
onlyfans_scraper2-1.2.dist-info/entry_points.txt
onlyfans_scraper2-1.2.dist-info/RECORD
