Metadata-Version: 2.1
Name: onlyfans-scraper2
Version: 1.2
Summary: automatically scrape onlyfans
Author: excludedBittern8
Author-email: excludedBittern8@riseup.net
Requires-Python: >=3.8,<4.0
Classifier: Programming Language :: Python :: 3
Classifier: Programming Language :: Python :: 3.8
Classifier: Programming Language :: Python :: 3.9
Classifier: Programming Language :: Python :: 3.10
Classifier: Programming Language :: Python :: 3.11
Requires-Dist: httpx (>=0.23.3,<0.24.0)
Requires-Dist: inquirerpy (>=0.3.4,<0.4.0)
Requires-Dist: revolution (>=0.3.0,<0.4.0)
Requires-Dist: schedule (>=1.1.0,<2.0.0)
Requires-Dist: setuptools (>=67.6.0,<68.0.0)
Requires-Dist: tqdm (>=4.65.0,<5.0.0)
